LICENSE
MANIFEST.in
README.rst
setup.py
addthis/__init__.py
addthis/api.py
addthis/exceptions.py
addthis/tests.py
addthis.egg-info/PKG-INFO
addthis.egg-info/SOURCES.txt
addthis.egg-info/dependency_links.txt
addthis.egg-info/requires.txt
addthis.egg-info/top_level.txt