Metadata-Version: 1.1
Name: addthis
Version: 0.1.2
Summary: A Python wrapper for the AddThis Analytics API
Home-page: https://github.com/creafz/python-addthis
Author: Alex Parinov
Author-email: creafz@gmail.com
License: MIT License
Download-URL: https://github.com/creafz/python-addthis/tarball/0.1.2
Platform: UNKNOWN
Classifier: Development Status :: 4 - Beta
Classifier: Intended Audience :: Developers
Classifier: License :: OSI Approved :: MIT License
Classifier: Programming Language :: Python
Classifier: Programming Language :: Python :: 2.6
Classifier: Programming Language :: Python :: 2.7
Classifier: Programming Language :: Python :: 3
Classifier: Programming Language :: Python :: 3.2
Classifier: Programming Language :: Python :: 3.3
Classifier: Programming Language :: Python :: 3.4
Classifier: Programming Language :: Python :: Implementation :: PyPy
